agent_sentinel/__init__.py
agent_sentinel/approval.py
agent_sentinel/compliance.py
agent_sentinel/cost.py
agent_sentinel/errors.py
agent_sentinel/guard.py
agent_sentinel/intervention.py
agent_sentinel/ledger.py
agent_sentinel/mcp.py
agent_sentinel/policy.py
agent_sentinel/py.typed
agent_sentinel/replay.py
agent_sentinel/retry.py
agent_sentinel/sync.py
agent_sentinel/integrations/__init__.py
agent_sentinel/integrations/crewai.py
agent_sentinel/integrations/langchain.py
agent_sentinel/integrations/llm.py
agent_sentinel/integrations/pricing.py
agentsentinel_sdk-0.1.0.dist-info/licenses/LICENSE
agentsentinel_sdk-0.1.0.dist-info/METADATA
agentsentinel_sdk-0.1.0.dist-info/WHEEL
agentsentinel_sdk-0.1.0.dist-info/top_level.txt
agentsentinel_sdk-0.1.0.dist-info/RECORD
