Metadata-Version: 2.4
Name: agentsentinel-sdk
Version: 0.1.0
Summary: Runtime authority and control for autonomous AI agents
Author-email: Agent Sentinel Team <hello@agentsentinel.dev>
License: MIT
Project-URL: Homepage, https://agentsentinel.dev
Project-URL: Source, https://github.com/agent-sentinel/agent-sentinel-sdk
Project-URL: Tracker, https://github.com/agent-sentinel/agent-sentinel-sdk/issues
Keywords: agents,llm,control,safety,governance,ai,authorization,circuit-breaker
Classifier: Development Status :: 3 - Alpha
Classifier: Intended Audience :: Developers
Classifier: Programming Language :: Python :: 3
Classifier: Programming Language :: Python :: 3.9
Classifier: Programming Language :: Python :: 3.10
Classifier: Programming Language :: Python :: 3.11
Classifier: Programming Language :: Python :: 3.12
Classifier: Programming Language :: Python :: 3.13
Classifier: Topic :: Software Development :: Libraries :: Python Modules
Classifier: Topic :: System :: Monitoring
Requires-Python: >=3.9
License-File: LICENSE
Requires-Dist: pydantic>=2.10.0
Requires-Dist: pyyaml>=6.0.0
Provides-Extra: remote
Requires-Dist: httpx>=0.28.0; extra == "remote"
Provides-Extra: langchain
Requires-Dist: langchain>=0.1.0; extra == "langchain"
Requires-Dist: langchain-core>=0.1.0; extra == "langchain"
Provides-Extra: crewai
Requires-Dist: crewai>=0.1.0; extra == "crewai"
Provides-Extra: llm
Requires-Dist: openai>=1.0.0; extra == "llm"
Requires-Dist: anthropic>=0.18.0; extra == "llm"
Requires-Dist: google-generativeai>=0.3.0; extra == "llm"
Provides-Extra: integrations
Requires-Dist: langchain>=0.1.0; extra == "integrations"
Requires-Dist: langchain-core>=0.1.0; extra == "integrations"
Requires-Dist: crewai>=0.1.0; extra == "integrations"
Requires-Dist: openai>=1.0.0; extra == "integrations"
Requires-Dist: anthropic>=0.18.0; extra == "integrations"
Requires-Dist: google-generativeai>=0.3.0; extra == "integrations"
Provides-Extra: all
Requires-Dist: httpx>=0.28.0; extra == "all"
Requires-Dist: langchain>=0.1.0; extra == "all"
Requires-Dist: langchain-core>=0.1.0; extra == "all"
Requires-Dist: crewai>=0.1.0; extra == "all"
Requires-Dist: openai>=1.0.0; extra == "all"
Requires-Dist: anthropic>=0.18.0; extra == "all"
Requires-Dist: google-generativeai>=0.3.0; extra == "all"
Provides-Extra: dev
Requires-Dist: pytest<9.0.0,>=7.0.0; extra == "dev"
Requires-Dist: pytest-asyncio>=0.21.0; extra == "dev"
Requires-Dist: pytest-cov>=4.0.0; extra == "dev"
Requires-Dist: ruff>=0.1.0; extra == "dev"
Requires-Dist: mypy>=1.0.0; extra == "dev"
Requires-Dist: httpx>=0.24.0; extra == "dev"
Dynamic: license-file
